setup.py
bin/dbod-api
dbod/__init__.py
dbod/config.py
dbod/api/__init__.py
dbod/api/api.py
dbod/api/attribute.py
dbod/api/base.py
dbod/api/fim.py
dbod/api/functionalalias.py
dbod/api/host.py
dbod/api/hostaliases.py
dbod/api/instance.py
dbod/api/metadata.py
dbod/api/rundeck.py
dbod/tests/__init__.py
dbod/tests/attribute_test.py
dbod/tests/config_test.py
dbod/tests/functionalalias_test.py
dbod/tests/host_test.py
dbod/tests/instance_test.py
dbod/tests/metadata_test.py
dbod/tests/rundeck_test.py
dbod_api.egg-info/PKG-INFO
dbod_api.egg-info/SOURCES.txt
dbod_api.egg-info/dependency_links.txt
dbod_api.egg-info/pbr.json
dbod_api.egg-info/requires.txt
dbod_api.egg-info/top_level.txt
static/api.cfg