Metadata-Version: 1.0
Name: dbod-api
Version: 0.8.0
Summary: DB On Demand REST API
Home-page: https://github.com/cerndb/dbod-api
Author: Ignacio Coterillo
Author-email: icot@cern.ch
License: GPLv3
Platform: UNKNOWN
